stoyled/__init__.py
stoyled/escapeSequences.py
stoyled/generateStyles.py
stoyled/moreStyles.py
stoyled-0.9.dist-info/LICENSE
stoyled-0.9.dist-info/METADATA
stoyled-0.9.dist-info/WHEEL
stoyled-0.9.dist-info/top_level.txt
stoyled-0.9.dist-info/RECORD
