Metadata-Version: 2.1
Name: stoyled
Version: 0.9
Summary: Simple Fancy Standard Outputs for python3
Home-page: https://github.com/naryal2580/stoyled
Author: Captain Nick Lucifer
Author-email: naryal2580@gmail.com
License: UNKNOWN
Download-URL: https://github.com/naryal2580/stoyled/tarball/master
Platform: UNKNOWN
Classifier: Programming Language :: Python :: 3
Classifier: License :: OSI Approved :: MIT License
Classifier: Environment :: Console
Classifier: Operating System :: OS Independent
Requires-Python: >=3
